[
  {
    "id": "ibrsc",
    "name": "Island Barn Sailing Club",
    "shortName": "IBSC",
    "contactEmail": "dave@theryderclan.co.uk",
    "contactName": "Dave Ryder",
    "logoUrl": null,
    "seasons": [
      {
        "id": "2526",
        "name": "2025-26",
        "status": "current"
      }
    ],
    "fleets": [
      {
        "type": "HandicapRange",
        "id": "fasthandicap",
        "name": "Fast handicap",
        "min": 0,
        "max": 1000
      },
      {
        "type": "HandicapRange",
        "id": "slowhandicap",
        "name": "Slow handicap",
        "min": 1000,
        "max": 9999
      },
      {
        "type": "BoatClass",
        "id": "topper",
        "boatClassId": "Topper"
      },
      {
        "type": "BoatClass",
        "id": "ilca7",
        "boatClassId": "ILCA 7"
      }
    ],
    "classes": [
      {
        "id": "29er",
        "name": "29er",
        "handicaps": [
          {
            "scheme": "PY",
            "value": 900
          }
        ]
      },
      {
        "id": "Blaze",
        "name": "Blaze",
        "handicaps": [
          {
            "scheme": "PY",
            "value": 1030
          }
        ]
      },
      {
        "id": "Enterprise",
        "name": "Enterprise",
        "handicaps": [
          {
            "scheme": "PY",
            "value": 1137
          }
        ]
      },
      {
        "id": "Hartley 12",
        "name": "Hartley 12",
        "handicaps": [
          {
            "scheme": "PY",
            "value": 1250
          }
        ]
      },
      {
        "id": "ILCA 4",
        "name": "ILCA 4",
        "handicaps": [
          {
            "scheme": "PY",
            "value": 1216
          }
        ]
      },
      {
        "id": "ILCA 6",
        "name": "ILCA 6",
        "handicaps": [
          {
            "scheme": "PY",
            "value": 1154
          }
        ]
      },
      {
        "id": "ILCA 7",
        "name": "ILCA 7",
        "handicaps": [
          {
            "scheme": "PY",
            "value": 1104
          }
        ]
      },
      {
        "id": "Phantom",
        "name": "Phantom",
        "handicaps": [
          {
            "scheme": "PY",
            "value": 998
          }
        ]
      },
      {
        "id": "ROOSTER 8.1",
        "name": "ROOSTER 8.1",
        "handicaps": [
          {
            "scheme": "PY",
            "value": 1021
          }
        ]
      },
      {
        "id": "Aero 5",
        "name": "Aero 5",
        "handicaps": [
          {
            "scheme": "PY",
            "value": 1139
          }
        ]
      },
      {
        "id": "Aero 6",
        "name": "Aero 6",
        "handicaps": [
          {
            "scheme": "PY",
            "value": 1099
          }
        ]
      },
      {
        "id": "Aero 7",
        "name": "Aero 7",
        "handicaps": [
          {
            "scheme": "PY",
            "value": 1063
          }
        ]
      },
      {
        "id": "Aero 9",
        "name": "Aero 9",
        "handicaps": [
          {
            "scheme": "PY",
            "value": 1005
          }
        ]
      },
      {
        "id": "RS Feva",
        "name": "RS Feva",
        "handicaps": [
          {
            "scheme": "PY",
            "value": 1280
          }
        ]
      },
      {
        "id": "RS Feva XL",
        "name": "RS Feva XL",
        "handicaps": [
          {
            "scheme": "PY",
            "value": 1244
          }
        ]
      },
      {
        "id": "RS Vaero",
        "name": "RS Vaero",
        "handicaps": [
          {
            "scheme": "PY",
            "value": 1095
          }
        ]
      },
      {
        "id": "RS300",
        "name": "RS300",
        "handicaps": [
          {
            "scheme": "PY",
            "value": 965
          }
        ]
      },
      {
        "id": "RS200",
        "name": "RS200",
        "handicaps": [
          {
            "scheme": "PY",
            "value": 1050
          }
        ]
      },
      {
        "id": "RS400",
        "name": "RS400",
        "handicaps": [
          {
            "scheme": "PY",
            "value": 942
          }
        ]
      },
      {
        "id": "RS600",
        "name": "RS600",
        "handicaps": [
          {
            "scheme": "PY",
            "value": 921
          }
        ]
      },
      {
        "id": "Rooster 8.1",
        "name": "Rooster 8.1",
        "handicaps": [
          {
            "scheme": "PY",
            "value": 1021
          }
        ]
      },
      {
        "id": "Solo",
        "name": "Solo",
        "handicaps": [
          {
            "scheme": "PY",
            "value": 1139
          }
        ]
      },
      {
        "id": "Streaker",
        "name": "Streaker",
        "handicaps": [
          {
            "scheme": "PY",
            "value": 1124
          }
        ]
      },
      {
        "id": "Topper",
        "name": "Topper",
        "handicaps": [
          {
            "scheme": "PY",
            "value": 1363
          }
        ]
      },
      {
        "id": "Topper 4.2",
        "name": "Topper 4.2",
        "handicaps": [
          {
            "scheme": "PY",
            "value": 1440
          }
        ]
      }
    ],
    "supportedHandicapSchemes": [
      "PY",
      "Personal"
    ]
  },
  {
    "id": "demo",
    "name": "Demo Club",
    "shortName": "DEMO",
    "contactEmail": "contact@democlub.org",
    "contactName": "Demo Contact",
    "logoUrl": null,
    "seasons": [
      {
        "id": "2425",
        "name": "2025-26",
        "status": "current"
      }
    ],
    "fleets": [
      {
        "type": "HandicapRange",
        "id": "fasthandicap",
        "name": "Fast handicap",
        "min": 0,
        "max": 1000
      },
      {
        "type": "HandicapRange",
        "id": "slowhandicap",
        "name": "Slow handicap",
        "min": 1000,
        "max": 9999
      },
      {
        "type": "BoatClass",
        "id": "topper",
        "boatClassId": "Topper"
      },
      {
        "type": "BoatClass",
        "id": "ilca7",
        "boatClassId": "ILCA 7"
      }
    ],
    "classes": [
      {
        "id": "29er",
        "name": "29er",
        "handicaps": [
          {
            "scheme": "PY",
            "value": 900
          }
        ]
      },
      {
        "id": "Blaze",
        "name": "Blaze",
        "handicaps": [
          {
            "scheme": "PY",
            "value": 1030
          }
        ]
      },
      {
        "id": "Enterprise",
        "name": "Enterprise",
        "handicaps": [
          {
            "scheme": "PY",
            "value": 1137
          }
        ]
      },
      {
        "id": "Hartley 12",
        "name": "Hartley 12",
        "handicaps": [
          {
            "scheme": "PY",
            "value": 1250
          }
        ]
      },
      {
        "id": "ILCA 4",
        "name": "ILCA 4",
        "handicaps": [
          {
            "scheme": "PY",
            "value": 1216
          }
        ]
      },
      {
        "id": "ILCA 6",
        "name": "ILCA 6",
        "handicaps": [
          {
            "scheme": "PY",
            "value": 1154
          }
        ]
      },
      {
        "id": "ILCA 7",
        "name": "ILCA 7",
        "handicaps": [
          {
            "scheme": "PY",
            "value": 1104
          }
        ]
      },
      {
        "id": "Phantom",
        "name": "Phantom",
        "handicaps": [
          {
            "scheme": "PY",
            "value": 998
          }
        ]
      },
      {
        "id": "ROOSTER 8.1",
        "name": "ROOSTER 8.1",
        "handicaps": [
          {
            "scheme": "PY",
            "value": 1021
          }
        ]
      },
      {
        "id": "Aero 5",
        "name": "Aero 5",
        "handicaps": [
          {
            "scheme": "PY",
            "value": 1139
          }
        ]
      },
      {
        "id": "Aero 6",
        "name": "Aero 6",
        "handicaps": [
          {
            "scheme": "PY",
            "value": 1099
          }
        ]
      },
      {
        "id": "Aero 7",
        "name": "Aero 7",
        "handicaps": [
          {
            "scheme": "PY",
            "value": 1063
          }
        ]
      },
      {
        "id": "Aero 9",
        "name": "Aero 9",
        "handicaps": [
          {
            "scheme": "PY",
            "value": 1005
          }
        ]
      },
      {
        "id": "RS Feva",
        "name": "RS Feva",
        "handicaps": [
          {
            "scheme": "PY",
            "value": 1280
          }
        ]
      },
      {
        "id": "RS Feva XL",
        "name": "RS Feva XL",
        "handicaps": [
          {
            "scheme": "PY",
            "value": 1244
          }
        ]
      },
      {
        "id": "RS Vaero",
        "name": "RS Vaero",
        "handicaps": [
          {
            "scheme": "PY",
            "value": 1095
          }
        ]
      },
      {
        "id": "RS300",
        "name": "RS300",
        "handicaps": [
          {
            "scheme": "PY",
            "value": 965
          }
        ]
      },
      {
        "id": "RS200",
        "name": "RS200",
        "handicaps": [
          {
            "scheme": "PY",
            "value": 1050
          }
        ]
      },
      {
        "id": "RS400",
        "name": "RS400",
        "handicaps": [
          {
            "scheme": "PY",
            "value": 942
          }
        ]
      },
      {
        "id": "RS600",
        "name": "RS600",
        "handicaps": [
          {
            "scheme": "PY",
            "value": 921
          }
        ]
      },
      {
        "id": "Rooster 8.1",
        "name": "Rooster 8.1",
        "handicaps": [
          {
            "scheme": "PY",
            "value": 1021
          }
        ]
      },
      {
        "id": "Solo",
        "name": "Solo",
        "handicaps": [
          {
            "scheme": "PY",
            "value": 1139
          }
        ]
      },
      {
        "id": "Streaker",
        "name": "Streaker",
        "handicaps": [
          {
            "scheme": "PY",
            "value": 1124
          }
        ]
      },
      {
        "id": "Topper",
        "name": "Topper",
        "handicaps": [
          {
            "scheme": "PY",
            "value": 1363
          }
        ]
      },
      {
        "id": "Topper 4.2",
        "name": "Topper 4.2",
        "handicaps": [
          {
            "scheme": "PY",
            "value": 1440
          }
        ]
      }
    ],
    "supportedHandicapSchemes": [
      "PY",
      "Personal"
    ]
  },
  {
    "id": "test",
    "name": "Test Club",
    "shortName": "TEST",
    "contactEmail": "contact@testclub.org",
    "contactName": "Test Contact",
    "logoUrl": null,
    "seasons": [
      {
        "id": "2526",
        "name": "2025-26",
        "status": "current"
      }
    ],
    "fleets": [
      {
        "type": "HandicapRange",
        "id": "fasthandicap",
        "name": "Fast handicap",
        "min": 0,
        "max": 1000
      },
      {
        "type": "HandicapRange",
        "id": "slowhandicap",
        "name": "Slow handicap",
        "min": 1000,
        "max": 9999
      },
      {
        "type": "BoatClass",
        "id": "topper",
        "boatClassId": "Topper"
      },
      {
        "type": "BoatClass",
        "id": "ilca7",
        "boatClassId": "ILCA 7"
      }
    ],
    "classes": [
      {
        "id": "29er",
        "name": "29er",
        "handicaps": [
          {
            "scheme": "PY",
            "value": 900
          }
        ]
      },
      {
        "id": "Blaze",
        "name": "Blaze",
        "handicaps": [
          {
            "scheme": "PY",
            "value": 1030
          }
        ]
      },
      {
        "id": "Enterprise",
        "name": "Enterprise",
        "handicaps": [
          {
            "scheme": "PY",
            "value": 1137
          }
        ]
      },
      {
        "id": "Hartley 12",
        "name": "Hartley 12",
        "handicaps": [
          {
            "scheme": "PY",
            "value": 1250
          }
        ]
      },
      {
        "id": "ILCA 4",
        "name": "ILCA 4",
        "handicaps": [
          {
            "scheme": "PY",
            "value": 1216
          }
        ]
      },
      {
        "id": "ILCA 6",
        "name": "ILCA 6",
        "handicaps": [
          {
            "scheme": "PY",
            "value": 1154
          }
        ]
      },
      {
        "id": "ILCA 7",
        "name": "ILCA 7",
        "handicaps": [
          {
            "scheme": "PY",
            "value": 1104
          }
        ]
      },
      {
        "id": "Phantom",
        "name": "Phantom",
        "handicaps": [
          {
            "scheme": "PY",
            "value": 998
          }
        ]
      },
      {
        "id": "ROOSTER 8.1",
        "name": "ROOSTER 8.1",
        "handicaps": [
          {
            "scheme": "PY",
            "value": 1021
          }
        ]
      },
      {
        "id": "Aero 5",
        "name": "Aero 5",
        "handicaps": [
          {
            "scheme": "PY",
            "value": 1139
          }
        ]
      },
      {
        "id": "Aero 6",
        "name": "Aero 6",
        "handicaps": [
          {
            "scheme": "PY",
            "value": 1099
          }
        ]
      },
      {
        "id": "Aero 7",
        "name": "Aero 7",
        "handicaps": [
          {
            "scheme": "PY",
            "value": 1063
          }
        ]
      },
      {
        "id": "Aero 9",
        "name": "Aero 9",
        "handicaps": [
          {
            "scheme": "PY",
            "value": 1005
          }
        ]
      },
      {
        "id": "RS Feva",
        "name": "RS Feva",
        "handicaps": [
          {
            "scheme": "PY",
            "value": 1280
          }
        ]
      },
      {
        "id": "RS Feva XL",
        "name": "RS Feva XL",
        "handicaps": [
          {
            "scheme": "PY",
            "value": 1244
          }
        ]
      },
      {
        "id": "RS Vaero",
        "name": "RS Vaero",
        "handicaps": [
          {
            "scheme": "PY",
            "value": 1095
          }
        ]
      },
      {
        "id": "RS300",
        "name": "RS300",
        "handicaps": [
          {
            "scheme": "PY",
            "value": 965
          }
        ]
      },
      {
        "id": "RS200",
        "name": "RS200",
        "handicaps": [
          {
            "scheme": "PY",
            "value": 1050
          }
        ]
      },
      {
        "id": "RS400",
        "name": "RS400",
        "handicaps": [
          {
            "scheme": "PY",
            "value": 942
          }
        ]
      },
      {
        "id": "RS600",
        "name": "RS600",
        "handicaps": [
          {
            "scheme": "PY",
            "value": 921
          }
        ]
      },
      {
        "id": "Rooster 8.1",
        "name": "Rooster 8.1",
        "handicaps": [
          {
            "scheme": "PY",
            "value": 1021
          }
        ]
      },
      {
        "id": "Solo",
        "name": "Solo",
        "handicaps": [
          {
            "scheme": "PY",
            "value": 1139
          }
        ]
      },
      {
        "id": "Streaker",
        "name": "Streaker",
        "handicaps": [
          {
            "scheme": "PY",
            "value": 1124
          }
        ]
      },
      {
        "id": "Topper",
        "name": "Topper",
        "handicaps": [
          {
            "scheme": "PY",
            "value": 1363
          }
        ]
      },
      {
        "id": "Topper 4.2",
        "name": "Topper 4.2",
        "handicaps": [
          {
            "scheme": "PY",
            "value": 1440
          }
        ]
      }
    ],
    "supportedHandicapSchemes": [
      "PY",
      "Personal"
    ]
  }
]